LICENSE
MANIFEST.in
setup.cfg
setup.py
archipel_agent_virtualmachine_storage.egg-info/PKG-INFO
archipel_agent_virtualmachine_storage.egg-info/SOURCES.txt
archipel_agent_virtualmachine_storage.egg-info/dependency_links.txt
archipel_agent_virtualmachine_storage.egg-info/entry_points.txt
archipel_agent_virtualmachine_storage.egg-info/not-zip-safe
archipel_agent_virtualmachine_storage.egg-info/requires.txt
archipel_agent_virtualmachine_storage.egg-info/top_level.txt
archipelagentvirtualmachinestorage/__init__.py
archipelagentvirtualmachinestorage/__init__.pyc
archipelagentvirtualmachinestorage/magic.py
archipelagentvirtualmachinestorage/storage.py
archipelagentvirtualmachinestorage/storage.pyc